pyqaai/__init__.py
pyqaai/main.py
pyqaai/core/__init__.py
pyqaai/core/code_analyser.py
pyqaai/core/config_loader.py
pyqaai/core/llm.py
pyqaai/core/report_generator.py
pyqaai/core/user_interface.py
pyqaai/models/__init__.py
pyqaai/models/models.py
pyqaai/static/__init__.py
pyqaai/static/constants.py
pyqaai/static/prompts.py
pyqaai-0.1.7.dist-info/LICENSE
pyqaai-0.1.7.dist-info/METADATA
pyqaai-0.1.7.dist-info/WHEEL
pyqaai-0.1.7.dist-info/entry_points.txt
pyqaai-0.1.7.dist-info/top_level.txt
pyqaai-0.1.7.dist-info/RECORD
