Metadata-Version: 2.1
Name: pyqaai
Version: 0.1.7
Summary: AI Driven Python QA CLI
Author: Thea Aviss
License: MIT License
Classifier: Programming Language :: Python :: 3
Classifier: License :: OSI Approved :: MIT License
Classifier: Operating System :: OS Independent
Requires-Python: >=3.10
License-File: LICENSE
Requires-Dist: openai
Requires-Dist: tqdm
Requires-Dist: inquirer
Requires-Dist: termcolor
Requires-Dist: requests
Requires-Dist: markdown
